{
  "project_name": "NKAT v12",
  "version": "12.0.0",
  "start_date": "2025-05-26T07:57:36.197037",
  "theoretical_completeness": 0.95,
  "breakthrough_potential": 0.88,
  "implementation_phases": [
    {
      "phase": 1,
      "name": "基盤構築",
      "duration_months": "1-3",
      "priority": "最高",
      "components": [
        "ConsciousnessIntegrationSystem",
        "QuantumInformationFramework",
        "NoncommutativeGeometryCore"
      ]
    },
    {
      "phase": 2,
      "name": "理論統合",
      "duration_months": "3-6",
      "priority": "高",
      "components": [
        "EllipticFunctionExtension",
        "CosmicRayCorrelation",
        "FourierHeatKernelTheory"
      ]
    },
    {
      "phase": 3,
      "name": "AI強化",
      "duration_months": "6-9",
      "priority": "中",
      "components": [
        "AIPredictionEnhancement",
        "AutoParameterOptimization",
        "RealtimeAdaptation"
      ]
    },
    {
      "phase": 4,
      "name": "統合検証",
      "duration_months": "9-12",
      "priority": "最高",
      "components": [
        "LargeScaleVerification",
        "TheoreticalValidation",
        "BreakthroughConfirmation"
      ]
    }
  ],
  "next_immediate_steps": [
    "意識統合システムの基本クラス設計",
    "量子情報エントロピー計算の実装",
    "高次元非可換多様体の数学的基盤構築",
    "GPU最適化とメモリ管理の改善"
  ]
}